pypolymlp
