Metadata-Version: 2.1
Name: pypolymlp
Version: 0.3.0
Summary: Generator of polynomial machine learning potentials.
Home-page: https://github.com/sekocha/pypolymlp
Author: Atsuto Seko
Author-email: seko@cms.mtl.kyoto-u.ac.jp
Maintainer: Atsuto Seko
Maintainer-email: seko@cms.mtl.kyoto-u.ac.jp
License: BSD-3-Clause
Platform: all
Provides: pypolymlp
Requires-Python: >=3.9
License-File: LICENSE
Requires-Dist: setuptools>=61.0
Requires-Dist: scikit-build
Requires-Dist: ninja
Requires-Dist: wheel
Requires-Dist: cmake
Requires-Dist: make
Requires-Dist: pybind11
Requires-Dist: pybind11-global
Requires-Dist: eigen
Requires-Dist: numpy
Requires-Dist: scipy
Requires-Dist: pyyaml
